hypers/__init__.py
hypers/types.py
hypers/core/__init__.py
hypers/core/array.py
hypers/exceptions/__init__.py
hypers/learning/__init__.py
hypers/learning/abundance.py
hypers/learning/decomposition.py
hypers/plotting/view/__init__.py
hypers/plotting/view/_hsiDialog.py
hypers/plotting/view/_form/__init__.py
hypers/plotting/view/_form/mainwindow.py
hypers/signal/__init__.py
hypers/signal/core.py
hypers-0.1.1.dist-info/LICENSE
hypers-0.1.1.dist-info/METADATA
hypers-0.1.1.dist-info/WHEEL
hypers-0.1.1.dist-info/top_level.txt
hypers-0.1.1.dist-info/RECORD
