Metadata-Version: 2.1
Name: hypers
Version: 0.1.1
Summary: Hyperspectral data analysis and machine learning
Home-page: https://github.com/priyankshah7/hypers
Author: Priyank Shah
Author-email: priyank.shah@kcl.ac.uk
License: BSD 3-Clause
Download-URL: https://github.com/priyankshah7/hypers/archive/v0.0.11.tar.gz
Keywords: hyperspectral,data-analysis,clustering,matrix-decompositions,hyperspectral-analysis,machine learning
Platform: UNKNOWN
Requires-Python: >=3.5.0
Requires-Dist: numpy
Requires-Dist: scipy
Requires-Dist: pyqt5
Requires-Dist: pyqtgraph
Requires-Dist: cvxopt
